main.py
mcp_miaokong_wsd-0.1.0.dist-info/METADATA
mcp_miaokong_wsd-0.1.0.dist-info/WHEEL
mcp_miaokong_wsd-0.1.0.dist-info/entry_points.txt
mcp_miaokong_wsd-0.1.0.dist-info/top_level.txt
mcp_miaokong_wsd-0.1.0.dist-info/RECORD
