Metadata-Version: 2.4
Name: mcp_miaokong_WSD
Version: 0.1.0
Summary: 让控制变得简单!
Requires-Python: >=3.11
Requires-Dist: build>=1.2.2.post1
Requires-Dist: httpx>=0.28.1
Requires-Dist: mcp>=1.8.0
Requires-Dist: requests>=2.32.3
